{
    "rooms": [
        {
            "roomid": 1,
            "roomName": "101",
            "type": "single",
            "accessible": true,
            "image": "/images/room2.jpg",
            "description": "Aenean porttitor mauris sit amet lacinia molestie. In posuere accumsan aliquet. Maecenas sit amet nisl massa. Interdum et malesuada fames ac ante.",
            "features": [
                "TV",
                "WiFi",
                "Safe"
            ],
            "roomPrice": 100
        },
        {
            "roomid": 2,
            "roomName": "113",
            "type": "Single",
            "accessible": true,
            "image": "https://www.mwtestconsultancy.co.uk/img/room1.jpg",
            "description": "Please enter a description for this room",
            "features": [
                "WiFi"
            ],
            "roomPrice": 100
        },
        {
            "roomid": 3,
            "roomName": "1085",
            "type": "Single",
            "accessible": false,
            "image": "https://www.mwtestconsultancy.co.uk/img/room1.jpg",
            "description": "555555555555555555555555555555555555555",
            "features": [
                "WiFi",
                "Safe"
            ],
            "roomPrice": 100
        },
        {
            "roomid": 4,
            "roomName": "1",
            "type": "Single",
            "accessible": false,
            "image": "https://www.mwtestconsultancy.co.uk/img/room1.jpg",
            "description": "Please enter a description for this room",
            "features": [
                "Radio"
            ],
            "roomPrice": 1
        },
        {
            "roomid": 5,
            "roomName": "108",
            "type": "Single",
            "accessible": false,
            "image": "https://www.mwtestconsultancy.co.uk/img/room1.jpg",
            "description": "Please enter a description for this room",
            "features": [
                "WiFi"
            ],
            "roomPrice": 100
        },
        {
            "roomid": 6,
            "roomName": "lol",
            "type": "Single",
            "accessible": false,
            "image": "https://www.mwtestconsultancy.co.uk/img/room1.jpg",
            "description": "Please enter a description for this room",
            "features": [
                "WiFi"
            ],
            "roomPrice": 5
        },
        {
            "roomid": 7,
            "roomName": "1",
            "type": "Single",
            "accessible": false,
            "image": "https://www.mwtestconsultancy.co.uk/img/room1.jpg",
            "description": "Please enter a description for this room",
            "features": [
                "Radio"
            ],
            "roomPrice": 1
        },
        {
            "roomid": 8,
            "roomName": "1",
            "type": "Single",
            "accessible": false,
            "image": "https://www.mwtestconsultancy.co.uk/img/room1.jpg",
            "description": "Please enter a description for this room",
            "features": [
                "Radio"
            ],
            "roomPrice": 1
        },
        {
            "roomid": 9,
            "roomName": "1",
            "type": "Single",
            "accessible": false,
            "image": "https://www.mwtestconsultancy.co.uk/img/room1.jpg",
            "description": "Please enter a description for this room",
            "features": [
                "Radio"
            ],
            "roomPrice": 1
        },
        {
            "roomid": 10,
            "roomName": "1",
            "type": "Single",
            "accessible": false,
            "image": "https://www.mwtestconsultancy.co.uk/img/room1.jpg",
            "description": "Please enter a description for this room",
            "features": [
                "Radio"
            ],
            "roomPrice": 1
        },
        {
            "roomid": 11,
            "roomName": "1",
            "type": "Single",
            "accessible": false,
            "image": "https://www.mwtestconsultancy.co.uk/img/room1.jpg",
            "description": "Please enter a description for this room",
            "features": [
                "Radio"
            ],
            "roomPrice": 1
        },
        {
            "roomid": 12,
            "roomName": "1",
            "type": "Single",
            "accessible": false,
            "image": "https://www.mwtestconsultancy.co.uk/img/room1.jpg",
            "description": "Please enter a description for this room",
            "features": [
                "Radio"
            ],
            "roomPrice": 1
        },
        {
            "roomid": 13,
            "roomName": "1",
            "type": "Single",
            "accessible": false,
            "image": "https://www.mwtestconsultancy.co.uk/img/room1.jpg",
            "description": "Please enter a description for this room",
            "features": [
                "Radio"
            ],
            "roomPrice": 1
        },
        {
            "roomid": 14,
            "roomName": "1",
            "type": "Single",
            "accessible": false,
            "image": "https://www.mwtestconsultancy.co.uk/img/room1.jpg",
            "description": "Please enter a description for this room",
            "features": [
                "Radio"
            ],
            "roomPrice": 1
        },
        {
            "roomid": 15,
            "roomName": "1",
            "type": "Single",
            "accessible": false,
            "image": "https://www.mwtestconsultancy.co.uk/img/room1.jpg",
            "description": "Please enter a description for this room",
            "features": [
                "Radio"
            ],
            "roomPrice": 1
        },
        {
            "roomid": 16,
            "roomName": "1",
            "type": "Single",
            "accessible": false,
            "image": "https://www.mwtestconsultancy.co.uk/img/room1.jpg",
            "description": "Please enter a description for this room",
            "features": [
                "Radio"
            ],
            "roomPrice": 1
        },
        {
            "roomid": 17,
            "roomName": "1",
            "type": "Single",
            "accessible": false,
            "image": "https://www.mwtestconsultancy.co.uk/img/room1.jpg",
            "description": "Please enter a description for this room",
            "features": [
                "Radio"
            ],
            "roomPrice": 1
        },
        {
            "roomid": 18,
            "roomName": "1",
            "type": "Single",
            "accessible": false,
            "image": "https://www.mwtestconsultancy.co.uk/img/room1.jpg",
            "description": "Please enter a description for this room",
            "features": [
                "Radio"
            ],
            "roomPrice": 1
        },
        {
            "roomid": 19,
            "roomName": "1",
            "type": "Single",
            "accessible": false,
            "image": "https://www.mwtestconsultancy.co.uk/img/room1.jpg",
            "description": "Please enter a description for this room",
            "features": [
                "Radio"
            ],
            "roomPrice": 1
        },
        {
            "roomid": 20,
            "roomName": "1",
            "type": "Single",
            "accessible": false,
            "image": "https://www.mwtestconsultancy.co.uk/img/room1.jpg",
            "description": "Please enter a description for this room",
            "features": [
                "Radio"
            ],
            "roomPrice": 1
        },
        {
            "roomid": 21,
            "roomName": "1",
            "type": "Single",
            "accessible": false,
            "image": "https://www.mwtestconsultancy.co.uk/img/room1.jpg",
            "description": "Please enter a description for this room",
            "features": [
                "Radio"
            ],
            "roomPrice": 1
        },
        {
            "roomid": 22,
            "roomName": "1",
            "type": "Single",
            "accessible": false,
            "image": "https://www.mwtestconsultancy.co.uk/img/room1.jpg",
            "description": "Please enter a description for this room",
            "features": [
                "Radio"
            ],
            "roomPrice": 1
        },
        {
            "roomid": 23,
            "roomName": "1",
            "type": "Single",
            "accessible": false,
            "image": "https://www.mwtestconsultancy.co.uk/img/room1.jpg",
            "description": "Please enter a description for this room",
            "features": [
                "Radio"
            ],
            "roomPrice": 1
        },
        {
            "roomid": 24,
            "roomName": "1",
            "type": "Single",
            "accessible": false,
            "image": "https://www.mwtestconsultancy.co.uk/img/room1.jpg",
            "description": "Please enter a description for this room",
            "features": [
                "Radio"
            ],
            "roomPrice": 1
        },
        {
            "roomid": 25,
            "roomName": "1",
            "type": "Single",
            "accessible": false,
            "image": "https://www.mwtestconsultancy.co.uk/img/room1.jpg",
            "description": "Please enter a description for this room",
            "features": [
                "Radio"
            ],
            "roomPrice": 1
        },
        {
            "roomid": 26,
            "roomName": "1",
            "type": "Single",
            "accessible": false,
            "image": "https://www.mwtestconsultancy.co.uk/img/room1.jpg",
            "description": "Please enter a description for this room",
            "features": [
                "Radio"
            ],
            "roomPrice": 1
        },
        {
            "roomid": 27,
            "roomName": "1",
            "type": "Single",
            "accessible": false,
            "image": "https://www.mwtestconsultancy.co.uk/img/room1.jpg",
            "description": "Please enter a description for this room",
            "features": [
                "Radio"
            ],
            "roomPrice": 1
        },
        {
            "roomid": 28,
            "roomName": "1",
            "type": "Single",
            "accessible": false,
            "image": "https://www.mwtestconsultancy.co.uk/img/room1.jpg",
            "description": "Please enter a description for this room",
            "features": [
                "Radio"
            ],
            "roomPrice": 1
        },
        {
            "roomid": 29,
            "roomName": "1",
            "type": "Single",
            "accessible": false,
            "image": "https://www.mwtestconsultancy.co.uk/img/room1.jpg",
            "description": "Please enter a description for this room",
            "features": [
                "Radio"
            ],
            "roomPrice": 1
        },
        {
            "roomid": 30,
            "roomName": "1",
            "type": "Single",
            "accessible": false,
            "image": "https://www.mwtestconsultancy.co.uk/img/room1.jpg",
            "description": "Please enter a description for this room",
            "features": [
                "Radio"
            ],
            "roomPrice": 1
        },
        {
            "roomid": 31,
            "roomName": "1",
            "type": "Single",
            "accessible": false,
            "image": "https://www.mwtestconsultancy.co.uk/img/room1.jpg",
            "description": "Please enter a description for this room",
            "features": [
                "Radio"
            ],
            "roomPrice": 1
        },
        {
            "roomid": 32,
            "roomName": "1",
            "type": "Single",
            "accessible": false,
            "image": "https://www.mwtestconsultancy.co.uk/img/room1.jpg",
            "description": "Please enter a description for this room",
            "features": [
                "Radio"
            ],
            "roomPrice": 1
        },
        {
            "roomid": 33,
            "roomName": "1",
            "type": "Single",
            "accessible": false,
            "image": "https://www.mwtestconsultancy.co.uk/img/room1.jpg",
            "description": "Please enter a description for this room",
            "features": [
                "Radio"
            ],
            "roomPrice": 1
        },
        {
            "roomid": 34,
            "roomName": "1",
            "type": "Single",
            "accessible": false,
            "image": "https://www.mwtestconsultancy.co.uk/img/room1.jpg",
            "description": "Please enter a description for this room",
            "features": [
                "Radio"
            ],
            "roomPrice": 1
        },
        {
            "roomid": 35,
            "roomName": "1",
            "type": "Single",
            "accessible": false,
            "image": "https://www.mwtestconsultancy.co.uk/img/room1.jpg",
            "description": "Please enter a description for this room",
            "features": [
                "Radio"
            ],
            "roomPrice": 1
        },
        {
            "roomid": 36,
            "roomName": "1",
            "type": "Single",
            "accessible": false,
            "image": "https://www.mwtestconsultancy.co.uk/img/room1.jpg",
            "description": "Please enter a description for this room",
            "features": [
                "Radio"
            ],
            "roomPrice": 1
        },
        {
            "roomid": 37,
            "roomName": "1",
            "type": "Single",
            "accessible": false,
            "image": "https://www.mwtestconsultancy.co.uk/img/room1.jpg",
            "description": "Please enter a description for this room",
            "features": [
                "Radio"
            ],
            "roomPrice": 1
        },
        {
            "roomid": 38,
            "roomName": "1",
            "type": "Single",
            "accessible": false,
            "image": "https://www.mwtestconsultancy.co.uk/img/room1.jpg",
            "description": "Please enter a description for this room",
            "features": [
                "Radio"
            ],
            "roomPrice": 1
        },
        {
            "roomid": 39,
            "roomName": "1",
            "type": "Single",
            "accessible": false,
            "image": "https://www.mwtestconsultancy.co.uk/img/room1.jpg",
            "description": "Please enter a description for this room",
            "features": [
                "Radio"
            ],
            "roomPrice": 1
        },
        {
            "roomid": 40,
            "roomName": "1",
            "type": "Single",
            "accessible": false,
            "image": "https://www.mwtestconsultancy.co.uk/img/room1.jpg",
            "description": "Please enter a description for this room",
            "features": [
                "Radio"
            ],
            "roomPrice": 1
        },
        {
            "roomid": 41,
            "roomName": "1",
            "type": "Single",
            "accessible": false,
            "image": "https://www.mwtestconsultancy.co.uk/img/room1.jpg",
            "description": "Please enter a description for this room",
            "features": [
                "Radio"
            ],
            "roomPrice": 1
        },
        {
            "roomid": 42,
            "roomName": "1",
            "type": "Single",
            "accessible": false,
            "image": "https://www.mwtestconsultancy.co.uk/img/room1.jpg",
            "description": "Please enter a description for this room",
            "features": [
                "Radio"
            ],
            "roomPrice": 1
        },
        {
            "roomid": 43,
            "roomName": "1",
            "type": "Single",
            "accessible": false,
            "image": "https://www.mwtestconsultancy.co.uk/img/room1.jpg",
            "description": "Please enter a description for this room",
            "features": [
                "Radio"
            ],
            "roomPrice": 1
        },
        {
            "roomid": 44,
            "roomName": "1",
            "type": "Single",
            "accessible": false,
            "image": "https://www.mwtestconsultancy.co.uk/img/room1.jpg",
            "description": "Please enter a description for this room",
            "features": [
                "Radio"
            ],
            "roomPrice": 1
        },
        {
            "roomid": 45,
            "roomName": "1",
            "type": "Single",
            "accessible": false,
            "image": "https://www.mwtestconsultancy.co.uk/img/room1.jpg",
            "description": "Please enter a description for this room",
            "features": [
                "Radio"
            ],
            "roomPrice": 1
        },
        {
            "roomid": 46,
            "roomName": "1",
            "type": "Single",
            "accessible": false,
            "image": "https://www.mwtestconsultancy.co.uk/img/room1.jpg",
            "description": "Please enter a description for this room",
            "features": [
                "Radio"
            ],
            "roomPrice": 1
        },
        {
            "roomid": 47,
            "roomName": "1",
            "type": "Single",
            "accessible": false,
            "image": "https://www.mwtestconsultancy.co.uk/img/room1.jpg",
            "description": "Please enter a description for this room",
            "features": [
                "Radio"
            ],
            "roomPrice": 1
        },
        {
            "roomid": 48,
            "roomName": "1",
            "type": "Single",
            "accessible": false,
            "image": "https://www.mwtestconsultancy.co.uk/img/room1.jpg",
            "description": "Please enter a description for this room",
            "features": [
                "Radio"
            ],
            "roomPrice": 1
        },
        {
            "roomid": 49,
            "roomName": "1",
            "type": "Single",
            "accessible": false,
            "image": "https://www.mwtestconsultancy.co.uk/img/room1.jpg",
            "description": "Please enter a description for this room",
            "features": [
                "Radio"
            ],
            "roomPrice": 1
        },
        {
            "roomid": 50,
            "roomName": "1",
            "type": "Single",
            "accessible": false,
            "image": "https://www.mwtestconsultancy.co.uk/img/room1.jpg",
            "description": "Please enter a description for this room",
            "features": [
                "Radio"
            ],
            "roomPrice": 1
        },
        {
            "roomid": 51,
            "roomName": "1",
            "type": "Single",
            "accessible": false,
            "image": "https://www.mwtestconsultancy.co.uk/img/room1.jpg",
            "description": "Please enter a description for this room",
            "features": [
                "Radio"
            ],
            "roomPrice": 1
        },
        {
            "roomid": 52,
            "roomName": "1",
            "type": "Single",
            "accessible": false,
            "image": "https://www.mwtestconsultancy.co.uk/img/room1.jpg",
            "description": "Please enter a description for this room",
            "features": [
                "Radio"
            ],
            "roomPrice": 1
        },
        {
            "roomid": 53,
            "roomName": "1",
            "type": "Single",
            "accessible": false,
            "image": "https://www.mwtestconsultancy.co.uk/img/room1.jpg",
            "description": "Please enter a description for this room",
            "features": [
                "Radio"
            ],
            "roomPrice": 1
        },
        {
            "roomid": 54,
            "roomName": "1",
            "type": "Single",
            "accessible": false,
            "image": "https://www.mwtestconsultancy.co.uk/img/room1.jpg",
            "description": "Please enter a description for this room",
            "features": [
                "Radio"
            ],
            "roomPrice": 1
        },
        {
            "roomid": 55,
            "roomName": "1",
            "type": "Single",
            "accessible": false,
            "image": "https://www.mwtestconsultancy.co.uk/img/room1.jpg",
            "description": "Please enter a description for this room",
            "features": [
                "Radio"
            ],
            "roomPrice": 1
        },
        {
            "roomid": 56,
            "roomName": "1",
            "type": "Single",
            "accessible": false,
            "image": "https://www.mwtestconsultancy.co.uk/img/room1.jpg",
            "description": "Please enter a description for this room",
            "features": [
                "Radio"
            ],
            "roomPrice": 1
        },
        {
            "roomid": 57,
            "roomName": "1",
            "type": "Single",
            "accessible": false,
            "image": "https://www.mwtestconsultancy.co.uk/img/room1.jpg",
            "description": "Please enter a description for this room",
            "features": [
                "Radio"
            ],
            "roomPrice": 1
        },
        {
            "roomid": 58,
            "roomName": "1",
            "type": "Single",
            "accessible": false,
            "image": "https://www.mwtestconsultancy.co.uk/img/room1.jpg",
            "description": "Please enter a description for this room",
            "features": [
                "Radio"
            ],
            "roomPrice": 1
        },
        {
            "roomid": 59,
            "roomName": "1",
            "type": "Single",
            "accessible": false,
            "image": "https://www.mwtestconsultancy.co.uk/img/room1.jpg",
            "description": "Please enter a description for this room",
            "features": [
                "Radio"
            ],
            "roomPrice": 1
        },
        {
            "roomid": 60,
            "roomName": "1",
            "type": "Single",
            "accessible": false,
            "image": "https://www.mwtestconsultancy.co.uk/img/room1.jpg",
            "description": "Please enter a description for this room",
            "features": [
                "Radio"
            ],
            "roomPrice": 1
        },
        {
            "roomid": 61,
            "roomName": "1",
            "type": "Single",
            "accessible": false,
            "image": "https://www.mwtestconsultancy.co.uk/img/room1.jpg",
            "description": "Please enter a description for this room",
            "features": [
                "Radio"
            ],
            "roomPrice": 1
        },
        {
            "roomid": 62,
            "roomName": "1",
            "type": "Single",
            "accessible": false,
            "image": "https://www.mwtestconsultancy.co.uk/img/room1.jpg",
            "description": "Please enter a description for this room",
            "features": [
                "Radio"
            ],
            "roomPrice": 1
        },
        {
            "roomid": 63,
            "roomName": "1",
            "type": "Single",
            "accessible": false,
            "image": "https://www.mwtestconsultancy.co.uk/img/room1.jpg",
            "description": "Please enter a description for this room",
            "features": [
                "Radio"
            ],
            "roomPrice": 1
        },
        {
            "roomid": 64,
            "roomName": "1",
            "type": "Single",
            "accessible": false,
            "image": "https://www.mwtestconsultancy.co.uk/img/room1.jpg",
            "description": "Please enter a description for this room",
            "features": [
                "Radio"
            ],
            "roomPrice": 1
        },
        {
            "roomid": 65,
            "roomName": "1",
            "type": "Single",
            "accessible": false,
            "image": "https://www.mwtestconsultancy.co.uk/img/room1.jpg",
            "description": "Please enter a description for this room",
            "features": [
                "Radio"
            ],
            "roomPrice": 1
        },
        {
            "roomid": 66,
            "roomName": "1",
            "type": "Single",
            "accessible": false,
            "image": "https://www.mwtestconsultancy.co.uk/img/room1.jpg",
            "description": "Please enter a description for this room",
            "features": [
                "Radio"
            ],
            "roomPrice": 1
        },
        {
            "roomid": 67,
            "roomName": "102",
            "type": "Single",
            "accessible": false,
            "image": "https://www.mwtestconsultancy.co.uk/img/room1.jpg",
            "description": "Please enter a description for this room",
            "features": [
                "WiFi",
                "TV"
            ],
            "roomPrice": 500
        },
        {
            "roomid": 68,
            "roomName": "103",
            "type": "Single",
            "accessible": false,
            "image": "https://www.mwtestconsultancy.co.uk/img/room1.jpg",
            "description": "Please enter a description for this room",
            "features": [],
            "roomPrice": 400
        },
        {
            "roomid": 69,
            "roomName": "1",
            "type": "Single",
            "accessible": false,
            "image": "https://www.mwtestconsultancy.co.uk/img/room1.jpg",
            "description": "Please enter a description for this room",
            "features": [
                "Radio"
            ],
            "roomPrice": 1
        },
        {
            "roomid": 70,
            "roomName": "105",
            "type": "Single",
            "accessible": false,
            "image": "https://www.mwtestconsultancy.co.uk/img/room1.jpg",
            "description": "Please enter a description for this room",
            "features": [],
            "roomPrice": 500
        },
        {
            "roomid": 71,
            "roomName": "1",
            "type": "Single",
            "accessible": false,
            "image": "https://www.mwtestconsultancy.co.uk/img/room1.jpg",
            "description": "Please enter a description for this room",
            "features": [
                "Radio"
            ],
            "roomPrice": 1
        },
        {
            "roomid": 72,
            "roomName": "1",
            "type": "Single",
            "accessible": false,
            "image": "https://www.mwtestconsultancy.co.uk/img/room1.jpg",
            "description": "Please enter a description for this room",
            "features": [
                "Radio"
            ],
            "roomPrice": 1
        },
        {
            "roomid": 73,
            "roomName": "-5",
            "type": "Single",
            "accessible": false,
            "image": "https://www.mwtestconsultancy.co.uk/img/room1.jpg",
            "description": "Please enter a description for this room",
            "features": [
                "WiFi"
            ],
            "roomPrice": 100
        },
        {
            "roomid": 74,
            "roomName": "1",
            "type": "Single",
            "accessible": false,
            "image": "https://www.mwtestconsultancy.co.uk/img/room1.jpg",
            "description": "Please enter a description for this room",
            "features": [
                "Radio"
            ],
            "roomPrice": 1
        },
        {
            "roomid": 75,
            "roomName": "1",
            "type": "Single",
            "accessible": false,
            "image": "https://www.mwtestconsultancy.co.uk/img/room1.jpg",
            "description": "Please enter a description for this room",
            "features": [
                "Radio"
            ],
            "roomPrice": 1
        },
        {
            "roomid": 76,
            "roomName": "1",
            "type": "Single",
            "accessible": false,
            "image": "https://www.mwtestconsultancy.co.uk/img/room1.jpg",
            "description": "Please enter a description for this room",
            "features": [
                "Radio"
            ],
            "roomPrice": 1
        },
        {
            "roomid": 77,
            "roomName": "102",
            "type": "Single",
            "accessible": false,
            "image": "https://www.mwtestconsultancy.co.uk/img/room1.jpg",
            "description": "Please enter a description for this room",
            "features": [
                "WiFi",
                "TV"
            ],
            "roomPrice": 500
        },
        {
            "roomid": 78,
            "roomName": "1",
            "type": "Single",
            "accessible": false,
            "image": "https://www.mwtestconsultancy.co.uk/img/room1.jpg",
            "description": "Please enter a description for this room",
            "features": [
                "Radio"
            ],
            "roomPrice": 1
        },
        {
            "roomid": 79,
            "roomName": "1",
            "type": "Single",
            "accessible": false,
            "image": "https://www.mwtestconsultancy.co.uk/img/room1.jpg",
            "description": "Please enter a description for this room",
            "features": [
                "Radio"
            ],
            "roomPrice": 1
        },
        {
            "roomid": 80,
            "roomName": "1",
            "type": "Single",
            "accessible": false,
            "image": "https://www.mwtestconsultancy.co.uk/img/room1.jpg",
            "description": "Please enter a description for this room",
            "features": [
                "Radio"
            ],
            "roomPrice": 1
        },
        {
            "roomid": 81,
            "roomName": "1",
            "type": "Single",
            "accessible": false,
            "image": "https://www.mwtestconsultancy.co.uk/img/room1.jpg",
            "description": "Please enter a description for this room",
            "features": [
                "Radio"
            ],
            "roomPrice": 1
        },
        {
            "roomid": 82,
            "roomName": "1",
            "type": "Single",
            "accessible": false,
            "image": "https://www.mwtestconsultancy.co.uk/img/room1.jpg",
            "description": "Please enter a description for this room",
            "features": [
                "Radio"
            ],
            "roomPrice": 1
        },
        {
            "roomid": 83,
            "roomName": "1",
            "type": "Single",
            "accessible": false,
            "image": "https://www.mwtestconsultancy.co.uk/img/room1.jpg",
            "description": "Please enter a description for this room",
            "features": [
                "Radio"
            ],
            "roomPrice": 1
        },
        {
            "roomid": 84,
            "roomName": "1",
            "type": "Single",
            "accessible": false,
            "image": "https://www.mwtestconsultancy.co.uk/img/room1.jpg",
            "description": "Please enter a description for this room",
            "features": [
                "Radio"
            ],
            "roomPrice": 1
        },
        {
            "roomid": 85,
            "roomName": "1",
            "type": "Single",
            "accessible": false,
            "image": "https://www.mwtestconsultancy.co.uk/img/room1.jpg",
            "description": "Please enter a description for this room",
            "features": [
                "Radio"
            ],
            "roomPrice": 1
        },
        {
            "roomid": 86,
            "roomName": "1",
            "type": "Single",
            "accessible": false,
            "image": "https://www.mwtestconsultancy.co.uk/img/room1.jpg",
            "description": "Please enter a description for this room",
            "features": [
                "Radio"
            ],
            "roomPrice": 1
        },
        {
            "roomid": 87,
            "roomName": "1",
            "type": "Single",
            "accessible": false,
            "image": "https://www.mwtestconsultancy.co.uk/img/room1.jpg",
            "description": "Please enter a description for this room",
            "features": [
                "Radio"
            ],
            "roomPrice": 1
        },
        {
            "roomid": 88,
            "roomName": "1",
            "type": "Single",
            "accessible": false,
            "image": "https://www.mwtestconsultancy.co.uk/img/room1.jpg",
            "description": "Please enter a description for this room",
            "features": [
                "Radio"
            ],
            "roomPrice": 1
        },
        {
            "roomid": 89,
            "roomName": "1",
            "type": "Single",
            "accessible": false,
            "image": "https://www.mwtestconsultancy.co.uk/img/room1.jpg",
            "description": "Please enter a description for this room",
            "features": [
                "Radio"
            ],
            "roomPrice": 1
        },
        {
            "roomid": 90,
            "roomName": "1",
            "type": "Single",
            "accessible": false,
            "image": "https://www.mwtestconsultancy.co.uk/img/room1.jpg",
            "description": "Please enter a description for this room",
            "features": [
                "Radio"
            ],
            "roomPrice": 1
        },
        {
            "roomid": 91,
            "roomName": "1",
            "type": "Single",
            "accessible": false,
            "image": "https://www.mwtestconsultancy.co.uk/img/room1.jpg",
            "description": "Please enter a description for this room",
            "features": [
                "Radio"
            ],
            "roomPrice": 1
        },
        {
            "roomid": 92,
            "roomName": "1",
            "type": "Single",
            "accessible": false,
            "image": "https://www.mwtestconsultancy.co.uk/img/room1.jpg",
            "description": "Please enter a description for this room",
            "features": [
                "Radio"
            ],
            "roomPrice": 1
        },
        {
            "roomid": 93,
            "roomName": "1",
            "type": "Single",
            "accessible": false,
            "image": "https://www.mwtestconsultancy.co.uk/img/room1.jpg",
            "description": "Please enter a description for this room",
            "features": [
                "Radio"
            ],
            "roomPrice": 1
        },
        {
            "roomid": 94,
            "roomName": "1",
            "type": "Single",
            "accessible": false,
            "image": "https://www.mwtestconsultancy.co.uk/img/room1.jpg",
            "description": "Please enter a description for this room",
            "features": [
                "Radio"
            ],
            "roomPrice": 1
        },
        {
            "roomid": 95,
            "roomName": "113",
            "type": "Single",
            "accessible": true,
            "image": "https://www.mwtestconsultancy.co.uk/img/room1.jpg",
            "description": "Please enter a description for this room",
            "features": [
                "WiFi"
            ],
            "roomPrice": 100
        },
        {
            "roomid": 96,
            "roomName": "1",
            "type": "Single",
            "accessible": false,
            "image": "https://www.mwtestconsultancy.co.uk/img/room1.jpg",
            "description": "Please enter a description for this room",
            "features": [
                "Radio"
            ],
            "roomPrice": 1
        },
        {
            "roomid": 97,
            "roomName": "1",
            "type": "Single",
            "accessible": false,
            "image": "https://www.mwtestconsultancy.co.uk/img/room1.jpg",
            "description": "Please enter a description for this room",
            "features": [
                "Radio"
            ],
            "roomPrice": 1
        },
        {
            "roomid": 98,
            "roomName": "1",
            "type": "Single",
            "accessible": false,
            "image": "https://www.mwtestconsultancy.co.uk/img/room1.jpg",
            "description": "Please enter a description for this room",
            "features": [
                "Radio"
            ],
            "roomPrice": 1
        },
        {
            "roomid": 99,
            "roomName": "108",
            "type": "Single",
            "accessible": false,
            "image": "https://www.mwtestconsultancy.co.uk/img/room1.jpg",
            "description": "Please enter a description for this room",
            "features": [
                "WiFi"
            ],
            "roomPrice": 100
        },
        {
            "roomid": 100,
            "roomName": "1",
            "type": "Single",
            "accessible": false,
            "image": "https://www.mwtestconsultancy.co.uk/img/room1.jpg",
            "description": "Please enter a description for this room",
            "features": [
                "Radio"
            ],
            "roomPrice": 1
        },
        {
            "roomid": 101,
            "roomName": "1",
            "type": "Single",
            "accessible": false,
            "image": "https://www.mwtestconsultancy.co.uk/img/room1.jpg",
            "description": "Please enter a description for this room",
            "features": [
                "Radio"
            ],
            "roomPrice": 1
        },
        {
            "roomid": 102,
            "roomName": "1",
            "type": "Single",
            "accessible": false,
            "image": "https://www.mwtestconsultancy.co.uk/img/room1.jpg",
            "description": "Please enter a description for this room",
            "features": [
                "Radio"
            ],
            "roomPrice": 1
        },
        {
            "roomid": 103,
            "roomName": "1",
            "type": "Single",
            "accessible": false,
            "image": "https://www.mwtestconsultancy.co.uk/img/room1.jpg",
            "description": "Please enter a description for this room",
            "features": [
                "Radio"
            ],
            "roomPrice": 1
        },
        {
            "roomid": 104,
            "roomName": "102",
            "type": "Single",
            "accessible": false,
            "image": "https://www.mwtestconsultancy.co.uk/img/room1.jpg",
            "description": "Please enter a description for this room",
            "features": [
                "WiFi"
            ],
            "roomPrice": 100
        },
        {
            "roomid": 105,
            "roomName": "1",
            "type": "Single",
            "accessible": false,
            "image": "https://www.mwtestconsultancy.co.uk/img/room1.jpg",
            "description": "Please enter a description for this room",
            "features": [
                "Radio"
            ],
            "roomPrice": 1
        },
        {
            "roomid": 106,
            "roomName": "1",
            "type": "Single",
            "accessible": false,
            "image": "https://www.mwtestconsultancy.co.uk/img/room1.jpg",
            "description": "Please enter a description for this room",
            "features": [
                "Radio"
            ],
            "roomPrice": 1
        },
        {
            "roomid": 107,
            "roomName": "1",
            "type": "Single",
            "accessible": false,
            "image": "https://www.mwtestconsultancy.co.uk/img/room1.jpg",
            "description": "Please enter a description for this room",
            "features": [
                "Radio"
            ],
            "roomPrice": 1
        },
        {
            "roomid": 108,
            "roomName": "1",
            "type": "Single",
            "accessible": false,
            "image": "https://www.mwtestconsultancy.co.uk/img/room1.jpg",
            "description": "Please enter a description for this room",
            "features": [
                "Radio"
            ],
            "roomPrice": 1
        },
        {
            "roomid": 109,
            "roomName": "1",
            "type": "Single",
            "accessible": false,
            "image": "https://www.mwtestconsultancy.co.uk/img/room1.jpg",
            "description": "Please enter a description for this room",
            "features": [
                "Radio"
            ],
            "roomPrice": 1
        },
        {
            "roomid": 110,
            "roomName": "1",
            "type": "Single",
            "accessible": false,
            "image": "https://www.mwtestconsultancy.co.uk/img/room1.jpg",
            "description": "Please enter a description for this room",
            "features": [
                "Radio"
            ],
            "roomPrice": 1
        },
        {
            "roomid": 111,
            "roomName": "1",
            "type": "Single",
            "accessible": false,
            "image": "https://www.mwtestconsultancy.co.uk/img/room1.jpg",
            "description": "Please enter a description for this room",
            "features": [
                "Radio"
            ],
            "roomPrice": 1
        },
        {
            "roomid": 112,
            "roomName": "1",
            "type": "Single",
            "accessible": false,
            "image": "https://www.mwtestconsultancy.co.uk/img/room1.jpg",
            "description": "Please enter a description for this room",
            "features": [
                "Radio"
            ],
            "roomPrice": 1
        },
        {
            "roomid": 113,
            "roomName": "1",
            "type": "Single",
            "accessible": false,
            "image": "https://www.mwtestconsultancy.co.uk/img/room1.jpg",
            "description": "Please enter a description for this room",
            "features": [
                "Radio"
            ],
            "roomPrice": 1
        },
        {
            "roomid": 114,
            "roomName": "1",
            "type": "Single",
            "accessible": false,
            "image": "https://www.mwtestconsultancy.co.uk/img/room1.jpg",
            "description": "Please enter a description for this room",
            "features": [
                "Radio"
            ],
            "roomPrice": 1
        },
        {
            "roomid": 115,
            "roomName": "1",
            "type": "Single",
            "accessible": false,
            "image": "https://www.mwtestconsultancy.co.uk/img/room1.jpg",
            "description": "Please enter a description for this room",
            "features": [
                "Radio"
            ],
            "roomPrice": 1
        },
        {
            "roomid": 116,
            "roomName": "1",
            "type": "Single",
            "accessible": false,
            "image": "https://www.mwtestconsultancy.co.uk/img/room1.jpg",
            "description": "Please enter a description for this room",
            "features": [
                "Radio"
            ],
            "roomPrice": 1
        },
        {
            "roomid": 117,
            "roomName": "1",
            "type": "Single",
            "accessible": false,
            "image": "https://www.mwtestconsultancy.co.uk/img/room1.jpg",
            "description": "Please enter a description for this room",
            "features": [
                "Radio"
            ],
            "roomPrice": 1
        },
        {
            "roomid": 118,
            "roomName": "1",
            "type": "Single",
            "accessible": false,
            "image": "https://www.mwtestconsultancy.co.uk/img/room1.jpg",
            "description": "Please enter a description for this room",
            "features": [
                "Radio"
            ],
            "roomPrice": 1
        },
        {
            "roomid": 119,
            "roomName": "1",
            "type": "Single",
            "accessible": false,
            "image": "https://www.mwtestconsultancy.co.uk/img/room1.jpg",
            "description": "Please enter a description for this room",
            "features": [
                "Radio"
            ],
            "roomPrice": 1
        },
        {
            "roomid": 120,
            "roomName": "1",
            "type": "Single",
            "accessible": false,
            "image": "https://www.mwtestconsultancy.co.uk/img/room1.jpg",
            "description": "Please enter a description for this room",
            "features": [
                "Radio"
            ],
            "roomPrice": 1
        },
        {
            "roomid": 121,
            "roomName": "1",
            "type": "Single",
            "accessible": false,
            "image": "https://www.mwtestconsultancy.co.uk/img/room1.jpg",
            "description": "Please enter a description for this room",
            "features": [
                "Radio"
            ],
            "roomPrice": 1
        },
        {
            "roomid": 122,
            "roomName": "1",
            "type": "Single",
            "accessible": false,
            "image": "https://www.mwtestconsultancy.co.uk/img/room1.jpg",
            "description": "Please enter a description for this room",
            "features": [
                "Radio"
            ],
            "roomPrice": 1
        },
        {
            "roomid": 123,
            "roomName": "1",
            "type": "Single",
            "accessible": false,
            "image": "https://www.mwtestconsultancy.co.uk/img/room1.jpg",
            "description": "Please enter a description for this room",
            "features": [
                "Radio"
            ],
            "roomPrice": 1
        },
        {
            "roomid": 124,
            "roomName": "1",
            "type": "Single",
            "accessible": false,
            "image": "https://www.mwtestconsultancy.co.uk/img/room1.jpg",
            "description": "Please enter a description for this room",
            "features": [
                "Radio"
            ],
            "roomPrice": 1
        },
        {
            "roomid": 125,
            "roomName": "1",
            "type": "Single",
            "accessible": false,
            "image": "https://www.mwtestconsultancy.co.uk/img/room1.jpg",
            "description": "Please enter a description for this room",
            "features": [
                "Radio"
            ],
            "roomPrice": 1
        },
        {
            "roomid": 126,
            "roomName": "1",
            "type": "Single",
            "accessible": false,
            "image": "https://www.mwtestconsultancy.co.uk/img/room1.jpg",
            "description": "Please enter a description for this room",
            "features": [
                "Radio"
            ],
            "roomPrice": 1
        },
        {
            "roomid": 127,
            "roomName": "1",
            "type": "Single",
            "accessible": false,
            "image": "https://www.mwtestconsultancy.co.uk/img/room1.jpg",
            "description": "Please enter a description for this room",
            "features": [
                "Radio"
            ],
            "roomPrice": 1
        },
        {
            "roomid": 128,
            "roomName": "101",
            "type": "Single",
            "accessible": false,
            "image": "https://www.mwtestconsultancy.co.uk/img/room1.jpg",
            "description": "Please enter a description for this room",
            "features": [
                "WiFi"
            ],
            "roomPrice": 2
        },
        {
            "roomid": 129,
            "roomName": "1",
            "type": "Single",
            "accessible": false,
            "image": "https://www.mwtestconsultancy.co.uk/img/room1.jpg",
            "description": "Please enter a description for this room",
            "features": [
                "Radio"
            ],
            "roomPrice": 1
        },
        {
            "roomid": 130,
            "roomName": "1",
            "type": "Single",
            "accessible": false,
            "image": "https://www.mwtestconsultancy.co.uk/img/room1.jpg",
            "description": "Please enter a description for this room",
            "features": [
                "Radio"
            ],
            "roomPrice": 1
        },
        {
            "roomid": 131,
            "roomName": "1",
            "type": "Single",
            "accessible": false,
            "image": "https://www.mwtestconsultancy.co.uk/img/room1.jpg",
            "description": "Please enter a description for this room",
            "features": [
                "Radio"
            ],
            "roomPrice": 1
        },
        {
            "roomid": 132,
            "roomName": "1",
            "type": "Single",
            "accessible": false,
            "image": "https://www.mwtestconsultancy.co.uk/img/room1.jpg",
            "description": "Please enter a description for this room",
            "features": [
                "Radio"
            ],
            "roomPrice": 1
        },
        {
            "roomid": 133,
            "roomName": "1",
            "type": "Single",
            "accessible": false,
            "image": "https://www.mwtestconsultancy.co.uk/img/room1.jpg",
            "description": "Please enter a description for this room",
            "features": [
                "Radio"
            ],
            "roomPrice": 1
        },
        {
            "roomid": 134,
            "roomName": "1",
            "type": "Single",
            "accessible": false,
            "image": "https://www.mwtestconsultancy.co.uk/img/room1.jpg",
            "description": "Please enter a description for this room",
            "features": [
                "Radio"
            ],
            "roomPrice": 1
        },
        {
            "roomid": 135,
            "roomName": "1",
            "type": "Single",
            "accessible": false,
            "image": "https://www.mwtestconsultancy.co.uk/img/room1.jpg",
            "description": "Please enter a description for this room",
            "features": [
                "Radio"
            ],
            "roomPrice": 1
        },
        {
            "roomid": 136,
            "roomName": "1",
            "type": "Single",
            "accessible": false,
            "image": "https://www.mwtestconsultancy.co.uk/img/room1.jpg",
            "description": "Please enter a description for this room",
            "features": [
                "Radio"
            ],
            "roomPrice": 1
        },
        {
            "roomid": 137,
            "roomName": "1",
            "type": "Single",
            "accessible": false,
            "image": "https://www.mwtestconsultancy.co.uk/img/room1.jpg",
            "description": "Please enter a description for this room",
            "features": [
                "Radio"
            ],
            "roomPrice": 1
        },
        {
            "roomid": 138,
            "roomName": "1",
            "type": "Single",
            "accessible": false,
            "image": "https://www.mwtestconsultancy.co.uk/img/room1.jpg",
            "description": "Please enter a description for this room",
            "features": [
                "Radio"
            ],
            "roomPrice": 1
        },
        {
            "roomid": 139,
            "roomName": "1",
            "type": "Single",
            "accessible": false,
            "image": "https://www.mwtestconsultancy.co.uk/img/room1.jpg",
            "description": "Please enter a description for this room",
            "features": [
                "Radio"
            ],
            "roomPrice": 1
        },
        {
            "roomid": 140,
            "roomName": "1",
            "type": "Single",
            "accessible": false,
            "image": "https://www.mwtestconsultancy.co.uk/img/room1.jpg",
            "description": "Please enter a description for this room",
            "features": [
                "Radio"
            ],
            "roomPrice": 1
        },
        {
            "roomid": 141,
            "roomName": "1",
            "type": "Single",
            "accessible": false,
            "image": "https://www.mwtestconsultancy.co.uk/img/room1.jpg",
            "description": "Please enter a description for this room",
            "features": [
                "Radio"
            ],
            "roomPrice": 1
        },
        {
            "roomid": 142,
            "roomName": "1",
            "type": "Single",
            "accessible": false,
            "image": "https://www.mwtestconsultancy.co.uk/img/room1.jpg",
            "description": "Please enter a description for this room",
            "features": [
                "Radio"
            ],
            "roomPrice": 1
        },
        {
            "roomid": 143,
            "roomName": "1",
            "type": "Single",
            "accessible": false,
            "image": "https://www.mwtestconsultancy.co.uk/img/room1.jpg",
            "description": "Please enter a description for this room",
            "features": [
                "Radio"
            ],
            "roomPrice": 1
        },
        {
            "roomid": 144,
            "roomName": "1",
            "type": "Single",
            "accessible": false,
            "image": "https://www.mwtestconsultancy.co.uk/img/room1.jpg",
            "description": "Please enter a description for this room",
            "features": [
                "Radio"
            ],
            "roomPrice": 1
        },
        {
            "roomid": 145,
            "roomName": "1",
            "type": "Single",
            "accessible": false,
            "image": "https://www.mwtestconsultancy.co.uk/img/room1.jpg",
            "description": "Please enter a description for this room",
            "features": [
                "Radio"
            ],
            "roomPrice": 1
        },
        {
            "roomid": 146,
            "roomName": "1",
            "type": "Single",
            "accessible": false,
            "image": "https://www.mwtestconsultancy.co.uk/img/room1.jpg",
            "description": "Please enter a description for this room",
            "features": [
                "Radio"
            ],
            "roomPrice": 1
        },
        {
            "roomid": 147,
            "roomName": "1",
            "type": "Single",
            "accessible": false,
            "image": "https://www.mwtestconsultancy.co.uk/img/room1.jpg",
            "description": "Please enter a description for this room",
            "features": [
                "Radio"
            ],
            "roomPrice": 1
        },
        {
            "roomid": 148,
            "roomName": "1",
            "type": "Single",
            "accessible": false,
            "image": "https://www.mwtestconsultancy.co.uk/img/room1.jpg",
            "description": "Please enter a description for this room",
            "features": [
                "Radio"
            ],
            "roomPrice": 1
        },
        {
            "roomid": 149,
            "roomName": "1",
            "type": "Single",
            "accessible": false,
            "image": "https://www.mwtestconsultancy.co.uk/img/room1.jpg",
            "description": "Please enter a description for this room",
            "features": [
                "Radio"
            ],
            "roomPrice": 1
        },
        {
            "roomid": 150,
            "roomName": "1",
            "type": "Single",
            "accessible": false,
            "image": "https://www.mwtestconsultancy.co.uk/img/room1.jpg",
            "description": "Please enter a description for this room",
            "features": [
                "Radio"
            ],
            "roomPrice": 1
        },
        {
            "roomid": 151,
            "roomName": "1",
            "type": "Single",
            "accessible": false,
            "image": "https://www.mwtestconsultancy.co.uk/img/room1.jpg",
            "description": "Please enter a description for this room",
            "features": [
                "Radio"
            ],
            "roomPrice": 1
        },
        {
            "roomid": 152,
            "roomName": "1",
            "type": "Single",
            "accessible": false,
            "image": "https://www.mwtestconsultancy.co.uk/img/room1.jpg",
            "description": "Please enter a description for this room",
            "features": [
                "Radio"
            ],
            "roomPrice": 1
        },
        {
            "roomid": 153,
            "roomName": "1",
            "type": "Single",
            "accessible": false,
            "image": "https://www.mwtestconsultancy.co.uk/img/room1.jpg",
            "description": "Please enter a description for this room",
            "features": [
                "Radio"
            ],
            "roomPrice": 1
        },
        {
            "roomid": 154,
            "roomName": "1",
            "type": "Single",
            "accessible": false,
            "image": "https://www.mwtestconsultancy.co.uk/img/room1.jpg",
            "description": "Please enter a description for this room",
            "features": [
                "Radio"
            ],
            "roomPrice": 1
        },
        {
            "roomid": 155,
            "roomName": "1",
            "type": "Single",
            "accessible": false,
            "image": "https://www.mwtestconsultancy.co.uk/img/room1.jpg",
            "description": "Please enter a description for this room",
            "features": [
                "Radio"
            ],
            "roomPrice": 1
        },
        {
            "roomid": 156,
            "roomName": "1",
            "type": "Single",
            "accessible": false,
            "image": "https://www.mwtestconsultancy.co.uk/img/room1.jpg",
            "description": "Please enter a description for this room",
            "features": [
                "Radio"
            ],
            "roomPrice": 1
        },
        {
            "roomid": 157,
            "roomName": "1",
            "type": "Single",
            "accessible": false,
            "image": "https://www.mwtestconsultancy.co.uk/img/room1.jpg",
            "description": "Please enter a description for this room",
            "features": [
                "Radio"
            ],
            "roomPrice": 1
        },
        {
            "roomid": 158,
            "roomName": "1",
            "type": "Single",
            "accessible": false,
            "image": "https://www.mwtestconsultancy.co.uk/img/room1.jpg",
            "description": "Please enter a description for this room",
            "features": [
                "Radio"
            ],
            "roomPrice": 1
        },
        {
            "roomid": 159,
            "roomName": "1",
            "type": "Single",
            "accessible": false,
            "image": "https://www.mwtestconsultancy.co.uk/img/room1.jpg",
            "description": "Please enter a description for this room",
            "features": [
                "Radio"
            ],
            "roomPrice": 1
        },
        {
            "roomid": 160,
            "roomName": "1",
            "type": "Single",
            "accessible": false,
            "image": "https://www.mwtestconsultancy.co.uk/img/room1.jpg",
            "description": "Please enter a description for this room",
            "features": [
                "Radio"
            ],
            "roomPrice": 1
        },
        {
            "roomid": 161,
            "roomName": "1",
            "type": "Single",
            "accessible": false,
            "image": "https://www.mwtestconsultancy.co.uk/img/room1.jpg",
            "description": "Please enter a description for this room",
            "features": [
                "Radio"
            ],
            "roomPrice": 1
        },
        {
            "roomid": 162,
            "roomName": "1",
            "type": "Single",
            "accessible": false,
            "image": "https://www.mwtestconsultancy.co.uk/img/room1.jpg",
            "description": "Please enter a description for this room",
            "features": [
                "Radio"
            ],
            "roomPrice": 1
        },
        {
            "roomid": 163,
            "roomName": "1",
            "type": "Single",
            "accessible": false,
            "image": "https://www.mwtestconsultancy.co.uk/img/room1.jpg",
            "description": "Please enter a description for this room",
            "features": [
                "Radio"
            ],
            "roomPrice": 1
        },
        {
            "roomid": 164,
            "roomName": "1",
            "type": "Single",
            "accessible": false,
            "image": "https://www.mwtestconsultancy.co.uk/img/room1.jpg",
            "description": "Please enter a description for this room",
            "features": [
                "Radio"
            ],
            "roomPrice": 1
        },
        {
            "roomid": 165,
            "roomName": "1",
            "type": "Single",
            "accessible": false,
            "image": "https://www.mwtestconsultancy.co.uk/img/room1.jpg",
            "description": "Please enter a description for this room",
            "features": [
                "Radio"
            ],
            "roomPrice": 1
        },
        {
            "roomid": 166,
            "roomName": "1",
            "type": "Single",
            "accessible": false,
            "image": "https://www.mwtestconsultancy.co.uk/img/room1.jpg",
            "description": "Please enter a description for this room",
            "features": [
                "Radio"
            ],
            "roomPrice": 1
        },
        {
            "roomid": 167,
            "roomName": "1",
            "type": "Single",
            "accessible": false,
            "image": "https://www.mwtestconsultancy.co.uk/img/room1.jpg",
            "description": "Please enter a description for this room",
            "features": [
                "Radio"
            ],
            "roomPrice": 1
        },
        {
            "roomid": 168,
            "roomName": "1",
            "type": "Single",
            "accessible": false,
            "image": "https://www.mwtestconsultancy.co.uk/img/room1.jpg",
            "description": "Please enter a description for this room",
            "features": [
                "Radio"
            ],
            "roomPrice": 1
        },
        {
            "roomid": 169,
            "roomName": "1",
            "type": "Single",
            "accessible": false,
            "image": "https://www.mwtestconsultancy.co.uk/img/room1.jpg",
            "description": "Please enter a description for this room",
            "features": [
                "Radio"
            ],
            "roomPrice": 1
        },
        {
            "roomid": 170,
            "roomName": "1",
            "type": "Single",
            "accessible": false,
            "image": "https://www.mwtestconsultancy.co.uk/img/room1.jpg",
            "description": "Please enter a description for this room",
            "features": [
                "Radio"
            ],
            "roomPrice": 1
        },
        {
            "roomid": 171,
            "roomName": "1",
            "type": "Single",
            "accessible": false,
            "image": "https://www.mwtestconsultancy.co.uk/img/room1.jpg",
            "description": "Please enter a description for this room",
            "features": [
                "Radio"
            ],
            "roomPrice": 1
        },
        {
            "roomid": 172,
            "roomName": "113",
            "type": "Single",
            "accessible": true,
            "image": "https://www.mwtestconsultancy.co.uk/img/room1.jpg",
            "description": "Please enter a description for this room",
            "features": [
                "WiFi"
            ],
            "roomPrice": 100
        },
        {
            "roomid": 173,
            "roomName": "1",
            "type": "Single",
            "accessible": false,
            "image": "https://www.mwtestconsultancy.co.uk/img/room1.jpg",
            "description": "Please enter a description for this room",
            "features": [
                "Radio"
            ],
            "roomPrice": 1
        },
        {
            "roomid": 174,
            "roomName": "1",
            "type": "Single",
            "accessible": false,
            "image": "https://www.mwtestconsultancy.co.uk/img/room1.jpg",
            "description": "Please enter a description for this room",
            "features": [
                "Radio"
            ],
            "roomPrice": 1
        },
        {
            "roomid": 175,
            "roomName": "1",
            "type": "Single",
            "accessible": false,
            "image": "https://www.mwtestconsultancy.co.uk/img/room1.jpg",
            "description": "Please enter a description for this room",
            "features": [
                "Radio"
            ],
            "roomPrice": 1
        },
        {
            "roomid": 176,
            "roomName": "1",
            "type": "Single",
            "accessible": false,
            "image": "https://www.mwtestconsultancy.co.uk/img/room1.jpg",
            "description": "Please enter a description for this room",
            "features": [
                "Radio"
            ],
            "roomPrice": 1
        },
        {
            "roomid": 177,
            "roomName": "1",
            "type": "Single",
            "accessible": false,
            "image": "https://www.mwtestconsultancy.co.uk/img/room1.jpg",
            "description": "Please enter a description for this room",
            "features": [
                "Radio"
            ],
            "roomPrice": 1
        },
        {
            "roomid": 178,
            "roomName": "1",
            "type": "Single",
            "accessible": false,
            "image": "https://www.mwtestconsultancy.co.uk/img/room1.jpg",
            "description": "Please enter a description for this room",
            "features": [
                "Radio"
            ],
            "roomPrice": 1
        },
        {
            "roomid": 179,
            "roomName": "1",
            "type": "Single",
            "accessible": false,
            "image": "https://www.mwtestconsultancy.co.uk/img/room1.jpg",
            "description": "Please enter a description for this room",
            "features": [
                "Radio"
            ],
            "roomPrice": 1
        },
        {
            "roomid": 180,
            "roomName": "102",
            "type": "Single",
            "accessible": false,
            "image": "https://www.mwtestconsultancy.co.uk/img/room1.jpg",
            "description": "Please enter a description for this room",
            "features": [
                "WiFi",
                "TV"
            ],
            "roomPrice": 500
        },
        {
            "roomid": 181,
            "roomName": "103",
            "type": "Single",
            "accessible": false,
            "image": "https://www.mwtestconsultancy.co.uk/img/room1.jpg",
            "description": "Please enter a description for this room",
            "features": [],
            "roomPrice": 400
        },
        {
            "roomid": 182,
            "roomName": "105",
            "type": "Single",
            "accessible": false,
            "image": "https://www.mwtestconsultancy.co.uk/img/room1.jpg",
            "description": "Please enter a description for this room",
            "features": [],
            "roomPrice": 500
        },
        {
            "roomid": 183,
            "roomName": "1",
            "type": "Single",
            "accessible": false,
            "image": "https://www.mwtestconsultancy.co.uk/img/room1.jpg",
            "description": "Please enter a description for this room",
            "features": [
                "Radio"
            ],
            "roomPrice": 1
        },
        {
            "roomid": 184,
            "roomName": "1",
            "type": "Single",
            "accessible": false,
            "image": "https://www.mwtestconsultancy.co.uk/img/room1.jpg",
            "description": "Please enter a description for this room",
            "features": [
                "Radio"
            ],
            "roomPrice": 1
        },
        {
            "roomid": 185,
            "roomName": "1",
            "type": "Single",
            "accessible": false,
            "image": "https://www.mwtestconsultancy.co.uk/img/room1.jpg",
            "description": "Please enter a description for this room",
            "features": [
                "Radio"
            ],
            "roomPrice": 1
        },
        {
            "roomid": 186,
            "roomName": "-5",
            "type": "Single",
            "accessible": false,
            "image": "https://www.mwtestconsultancy.co.uk/img/room1.jpg",
            "description": "Please enter a description for this room",
            "features": [
                "WiFi"
            ],
            "roomPrice": 100
        },
        {
            "roomid": 187,
            "roomName": "1",
            "type": "Single",
            "accessible": false,
            "image": "https://www.mwtestconsultancy.co.uk/img/room1.jpg",
            "description": "Please enter a description for this room",
            "features": [
                "Radio"
            ],
            "roomPrice": 1
        },
        {
            "roomid": 188,
            "roomName": "1",
            "type": "Single",
            "accessible": false,
            "image": "https://www.mwtestconsultancy.co.uk/img/room1.jpg",
            "description": "Please enter a description for this room",
            "features": [
                "Radio"
            ],
            "roomPrice": 1
        },
        {
            "roomid": 189,
            "roomName": "1",
            "type": "Single",
            "accessible": false,
            "image": "https://www.mwtestconsultancy.co.uk/img/room1.jpg",
            "description": "Please enter a description for this room",
            "features": [
                "Radio"
            ],
            "roomPrice": 1
        },
        {
            "roomid": 190,
            "roomName": "1",
            "type": "Single",
            "accessible": false,
            "image": "https://www.mwtestconsultancy.co.uk/img/room1.jpg",
            "description": "Please enter a description for this room",
            "features": [
                "Radio"
            ],
            "roomPrice": 1
        },
        {
            "roomid": 191,
            "roomName": "1",
            "type": "Single",
            "accessible": false,
            "image": "https://www.mwtestconsultancy.co.uk/img/room1.jpg",
            "description": "Please enter a description for this room",
            "features": [
                "Radio"
            ],
            "roomPrice": 1
        },
        {
            "roomid": 192,
            "roomName": "1",
            "type": "Single",
            "accessible": false,
            "image": "https://www.mwtestconsultancy.co.uk/img/room1.jpg",
            "description": "Please enter a description for this room",
            "features": [
                "Radio"
            ],
            "roomPrice": 1
        },
        {
            "roomid": 193,
            "roomName": "1",
            "type": "Single",
            "accessible": false,
            "image": "https://www.mwtestconsultancy.co.uk/img/room1.jpg",
            "description": "Please enter a description for this room",
            "features": [
                "Radio"
            ],
            "roomPrice": 1
        },
        {
            "roomid": 194,
            "roomName": "1",
            "type": "Single",
            "accessible": false,
            "image": "https://www.mwtestconsultancy.co.uk/img/room1.jpg",
            "description": "Please enter a description for this room",
            "features": [
                "Radio"
            ],
            "roomPrice": 1
        },
        {
            "roomid": 195,
            "roomName": "1",
            "type": "Single",
            "accessible": false,
            "image": "https://www.mwtestconsultancy.co.uk/img/room1.jpg",
            "description": "Please enter a description for this room",
            "features": [
                "Radio"
            ],
            "roomPrice": 1
        },
        {
            "roomid": 196,
            "roomName": "1",
            "type": "Single",
            "accessible": false,
            "image": "https://www.mwtestconsultancy.co.uk/img/room1.jpg",
            "description": "Please enter a description for this room",
            "features": [
                "Radio"
            ],
            "roomPrice": 1
        },
        {
            "roomid": 197,
            "roomName": "102",
            "type": "Single",
            "accessible": false,
            "image": "https://www.mwtestconsultancy.co.uk/img/room1.jpg",
            "description": "Please enter a description for this room",
            "features": [
                "WiFi",
                "TV"
            ],
            "roomPrice": 500
        },
        {
            "roomid": 198,
            "roomName": "1",
            "type": "Single",
            "accessible": false,
            "image": "https://www.mwtestconsultancy.co.uk/img/room1.jpg",
            "description": "Please enter a description for this room",
            "features": [
                "Radio"
            ],
            "roomPrice": 1
        },
        {
            "roomid": 199,
            "roomName": "1",
            "type": "Single",
            "accessible": false,
            "image": "https://www.mwtestconsultancy.co.uk/img/room1.jpg",
            "description": "Please enter a description for this room",
            "features": [
                "Radio"
            ],
            "roomPrice": 1
        },
        {
            "roomid": 200,
            "roomName": "1",
            "type": "Single",
            "accessible": false,
            "image": "https://www.mwtestconsultancy.co.uk/img/room1.jpg",
            "description": "Please enter a description for this room",
            "features": [
                "Radio"
            ],
            "roomPrice": 1
        },
        {
            "roomid": 201,
            "roomName": "1",
            "type": "Single",
            "accessible": false,
            "image": "https://www.mwtestconsultancy.co.uk/img/room1.jpg",
            "description": "Please enter a description for this room",
            "features": [
                "Radio"
            ],
            "roomPrice": 1
        },
        {
            "roomid": 202,
            "roomName": "1",
            "type": "Single",
            "accessible": false,
            "image": "https://www.mwtestconsultancy.co.uk/img/room1.jpg",
            "description": "Please enter a description for this room",
            "features": [
                "Radio"
            ],
            "roomPrice": 1
        },
        {
            "roomid": 203,
            "roomName": "1",
            "type": "Single",
            "accessible": false,
            "image": "https://www.mwtestconsultancy.co.uk/img/room1.jpg",
            "description": "Please enter a description for this room",
            "features": [
                "Radio"
            ],
            "roomPrice": 1
        },
        {
            "roomid": 204,
            "roomName": "1",
            "type": "Single",
            "accessible": false,
            "image": "https://www.mwtestconsultancy.co.uk/img/room1.jpg",
            "description": "Please enter a description for this room",
            "features": [
                "Radio"
            ],
            "roomPrice": 1
        },
        {
            "roomid": 205,
            "roomName": "1",
            "type": "Single",
            "accessible": false,
            "image": "https://www.mwtestconsultancy.co.uk/img/room1.jpg",
            "description": "Please enter a description for this room",
            "features": [
                "Radio"
            ],
            "roomPrice": 1
        },
        {
            "roomid": 206,
            "roomName": "1",
            "type": "Single",
            "accessible": false,
            "image": "https://www.mwtestconsultancy.co.uk/img/room1.jpg",
            "description": "Please enter a description for this room",
            "features": [
                "Radio"
            ],
            "roomPrice": 1
        },
        {
            "roomid": 207,
            "roomName": "113",
            "type": "Single",
            "accessible": true,
            "image": "https://www.mwtestconsultancy.co.uk/img/room1.jpg",
            "description": "Please enter a description for this room",
            "features": [
                "WiFi"
            ],
            "roomPrice": 100
        },
        {
            "roomid": 208,
            "roomName": "1",
            "type": "Single",
            "accessible": false,
            "image": "https://www.mwtestconsultancy.co.uk/img/room1.jpg",
            "description": "Please enter a description for this room",
            "features": [
                "Radio"
            ],
            "roomPrice": 1
        },
        {
            "roomid": 209,
            "roomName": "1",
            "type": "Single",
            "accessible": false,
            "image": "https://www.mwtestconsultancy.co.uk/img/room1.jpg",
            "description": "Please enter a description for this room",
            "features": [
                "Radio"
            ],
            "roomPrice": 1
        },
        {
            "roomid": 210,
            "roomName": "1",
            "type": "Single",
            "accessible": false,
            "image": "https://www.mwtestconsultancy.co.uk/img/room1.jpg",
            "description": "Please enter a description for this room",
            "features": [
                "Radio"
            ],
            "roomPrice": 1
        },
        {
            "roomid": 211,
            "roomName": "108",
            "type": "Single",
            "accessible": false,
            "image": "https://www.mwtestconsultancy.co.uk/img/room1.jpg",
            "description": "Please enter a description for this room",
            "features": [
                "WiFi"
            ],
            "roomPrice": 100
        },
        {
            "roomid": 212,
            "roomName": "110",
            "type": "Double",
            "accessible": false,
            "image": "https://www.mwtestconsultancy.co.uk/img/room1.jpg",
            "description": "Please enter a description for this room",
            "features": [],
            "roomPrice": 100
        },
        {
            "roomid": 213,
            "roomName": "1",
            "type": "Single",
            "accessible": false,
            "image": "https://www.mwtestconsultancy.co.uk/img/room1.jpg",
            "description": "Please enter a description for this room",
            "features": [
                "Radio"
            ],
            "roomPrice": 1
        },
        {
            "roomid": 214,
            "roomName": "1",
            "type": "Single",
            "accessible": false,
            "image": "https://www.mwtestconsultancy.co.uk/img/room1.jpg",
            "description": "Please enter a description for this room",
            "features": [
                "Radio"
            ],
            "roomPrice": 1
        },
        {
            "roomid": 215,
            "roomName": "102",
            "type": "Single",
            "accessible": false,
            "image": "https://www.mwtestconsultancy.co.uk/img/room1.jpg",
            "description": "Please enter a description for this room",
            "features": [
                "WiFi"
            ],
            "roomPrice": 100
        },
        {
            "roomid": 216,
            "roomName": "1",
            "type": "Single",
            "accessible": false,
            "image": "https://www.mwtestconsultancy.co.uk/img/room1.jpg",
            "description": "Please enter a description for this room",
            "features": [
                "Radio"
            ],
            "roomPrice": 1
        },
        {
            "roomid": 217,
            "roomName": "1",
            "type": "Single",
            "accessible": false,
            "image": "https://www.mwtestconsultancy.co.uk/img/room1.jpg",
            "description": "Please enter a description for this room",
            "features": [
                "Radio"
            ],
            "roomPrice": 1
        },
        {
            "roomid": 218,
            "roomName": "1",
            "type": "Single",
            "accessible": false,
            "image": "https://www.mwtestconsultancy.co.uk/img/room1.jpg",
            "description": "Please enter a description for this room",
            "features": [
                "Radio"
            ],
            "roomPrice": 1
        },
        {
            "roomid": 219,
            "roomName": "1",
            "type": "Single",
            "accessible": false,
            "image": "https://www.mwtestconsultancy.co.uk/img/room1.jpg",
            "description": "Please enter a description for this room",
            "features": [
                "Radio"
            ],
            "roomPrice": 1
        },
        {
            "roomid": 220,
            "roomName": "1",
            "type": "Single",
            "accessible": false,
            "image": "https://www.mwtestconsultancy.co.uk/img/room1.jpg",
            "description": "Please enter a description for this room",
            "features": [
                "Radio"
            ],
            "roomPrice": 1
        },
        {
            "roomid": 221,
            "roomName": "1",
            "type": "Single",
            "accessible": false,
            "image": "https://www.mwtestconsultancy.co.uk/img/room1.jpg",
            "description": "Please enter a description for this room",
            "features": [
                "Radio"
            ],
            "roomPrice": 1
        },
        {
            "roomid": 222,
            "roomName": "1",
            "type": "Single",
            "accessible": false,
            "image": "https://www.mwtestconsultancy.co.uk/img/room1.jpg",
            "description": "Please enter a description for this room",
            "features": [
                "Radio"
            ],
            "roomPrice": 1
        },
        {
            "roomid": 223,
            "roomName": "1",
            "type": "Single",
            "accessible": false,
            "image": "https://www.mwtestconsultancy.co.uk/img/room1.jpg",
            "description": "Please enter a description for this room",
            "features": [
                "Radio"
            ],
            "roomPrice": 1
        },
        {
            "roomid": 224,
            "roomName": "1",
            "type": "Single",
            "accessible": false,
            "image": "https://www.mwtestconsultancy.co.uk/img/room1.jpg",
            "description": "Please enter a description for this room",
            "features": [
                "Radio"
            ],
            "roomPrice": 1
        },
        {
            "roomid": 225,
            "roomName": "1",
            "type": "Single",
            "accessible": false,
            "image": "https://www.mwtestconsultancy.co.uk/img/room1.jpg",
            "description": "Please enter a description for this room",
            "features": [
                "Radio"
            ],
            "roomPrice": 1
        },
        {
            "roomid": 226,
            "roomName": "1",
            "type": "Single",
            "accessible": false,
            "image": "https://www.mwtestconsultancy.co.uk/img/room1.jpg",
            "description": "Please enter a description for this room",
            "features": [
                "Radio"
            ],
            "roomPrice": 1
        }
    ]
}